[
  {
    "timestamp" : "00:00.001-00:03.740",
    "text" : "And now the numbers in French without English prompts."
  },
  {
    "timestamp" : "00:03.740-00:07.440",
    "text" : "You'll find these at the end of the accompanying booklet."
  },
  {
    "timestamp" : "00:07.440-00:28.280",
    "text" : "Cinq."
  },
  {
    "timestamp" : "00:28.280-00:31.460",
    "text" : "Six."
  },
  {
    "text" : "Sept.",
    "timestamp" : "00:31.460-00:34.720"
  },
  {
    "timestamp" : "00:34.720-00:37.840",
    "text" : "Huit."
  },
  {
    "text" : "Neuf.",
    "timestamp" : "00:37.840-00:41.220"
  },
  {
    "timestamp" : "00:41.220-00:44.440",
    "text" : "Dix."
  },
  {
    "timestamp" : "00:44.440-00:47.860",
    "text" : "Onze."
  },
  {
    "timestamp" : "00:47.860-00:50.980",
    "text" : "Douze."
  },
  {
    "text" : "Treize.",
    "timestamp" : "00:50.980-00:54.100"
  },
  {
    "text" : "Quatorze.",
    "timestamp" : "00:54.100-00:57.160"
  },
  {
    "text" : "Quinze.",
    "timestamp" : "00:57.720-01:00.260"
  },
  {
    "text" : "Seize.",
    "timestamp" : "01:00.260-01:03.440"
  },
  {
    "timestamp" : "01:03.440-01:06.780",
    "text" : "Dix-sept."
  },
  {
    "timestamp" : "01:06.780-01:10.060",
    "text" : "Dix-huit."
  },
  {
    "text" : "Dix-neuf.",
    "timestamp" : "01:10.060-01:13.400"
  },
  {
    "timestamp" : "01:13.400-01:16.420",
    "text" : "Vingt."
  },
  {
    "text" : "Vingt-et-un.",
    "timestamp" : "01:16.420-01:19.660"
  },
  {
    "timestamp" : "01:22.100-01:23.220",
    "text" : "Vingt-deux."
  },
  {
    "text" : "Vingt-trois.",
    "timestamp" : "01:23.220-01:26.500"
  },
  {
    "text" : "Vingt-quatre.",
    "timestamp" : "01:26.500-01:29.940"
  },
  {
    "text" : "Vingt-cinq.",
    "timestamp" : "01:29.940-01:33.240"
  },
  {
    "text" : "Vingt-six.",
    "timestamp" : "01:33.240-01:36.460"
  },
  {
    "text" : "Vingt-sept.",
    "timestamp" : "01:36.460-01:39.740"
  },
  {
    "text" : "Vingt-huit.",
    "timestamp" : "01:39.740-01:43.020"
  },
  {
    "text" : "Vingt-neuf.",
    "timestamp" : "01:43.020-01:46.620"
  },
  {
    "text" : "30",
    "timestamp" : "01:46.720-01:49.980"
  },
  {
    "timestamp" : "01:49.980-01:53.040",
    "text" : "31"
  },
  {
    "text" : "32",
    "timestamp" : "01:53.040-01:56.720"
  },
  {
    "text" : "33",
    "timestamp" : "01:56.720-01:59.980"
  },
  {
    "text" : "34",
    "timestamp" : "01:59.980-02:03.460"
  },
  {
    "text" : "35",
    "timestamp" : "02:03.460-02:06.880"
  },
  {
    "text" : "36",
    "timestamp" : "02:06.880-02:09.960"
  },
  {
    "text" : "37",
    "timestamp" : "02:09.960-02:13.160"
  },
  {
    "timestamp" : "02:13.160-02:16.400",
    "text" : "38"
  },
  {
    "text" : "39",
    "timestamp" : "02:16.400-02:19.600"
  },
  {
    "text" : "40",
    "timestamp" : "02:19.600-02:22.800"
  },
  {
    "text" : "41",
    "timestamp" : "02:22.800-02:26.020"
  },
  {
    "text" : "42",
    "timestamp" : "02:26.020-02:29.380"
  },
  {
    "text" : "43",
    "timestamp" : "02:29.380-02:32.760"
  },
  {
    "text" : "44",
    "timestamp" : "02:32.760-02:36.300"
  },
  {
    "timestamp" : "02:36.300-02:39.860",
    "text" : "45"
  },
  {
    "text" : "46",
    "timestamp" : "02:39.860-02:43.300"
  },
  {
    "text" : "46",
    "timestamp" : "02:43.300-02:46.080"
  },
  {
    "timestamp" : "02:46.080-02:46.900",
    "text" : "47"
  },
  {
    "timestamp" : "02:46.900-02:50.380",
    "text" : "48"
  },
  {
    "text" : "49",
    "timestamp" : "02:50.380-02:53.920"
  },
  {
    "timestamp" : "02:53.920-02:57.200",
    "text" : "50"
  },
  {
    "timestamp" : "02:57.200-03:00.400",
    "text" : "51"
  },
  {
    "text" : "52",
    "timestamp" : "03:00.400-03:03.800"
  },
  {
    "text" : "53",
    "timestamp" : "03:03.800-03:07.200"
  },
  {
    "text" : "54",
    "timestamp" : "03:07.200-03:11.240"
  },
  {
    "text" : "55",
    "timestamp" : "03:11.240-03:13.600"
  },
  {
    "timestamp" : "03:13.600-03:14.740",
    "text" : "55"
  },
  {
    "text" : "56",
    "timestamp" : "03:14.740-03:18.320"
  },
  {
    "timestamp" : "03:18.320-03:21.900",
    "text" : "57"
  },
  {
    "text" : "58",
    "timestamp" : "03:21.900-03:25.400"
  },
  {
    "timestamp" : "03:25.400-03:29.180",
    "text" : "59"
  },
  {
    "timestamp" : "03:29.180-03:34.380",
    "text" : "60"
  },
  {
    "timestamp" : "03:34.380-03:35.280",
    "text" : "60"
  },
  {
    "text" : "61",
    "timestamp" : "03:35.280-03:35.580"
  },
  {
    "timestamp" : "03:35.580-03:36.560",
    "text" : "62"
  },
  {
    "text" : "62",
    "timestamp" : "03:36.560-03:38.560"
  },
  {
    "text" : "62",
    "timestamp" : "03:38.560-03:39.560"
  },
  {
    "text" : "63",
    "timestamp" : "03:39.560-03:42.560"
  },
  {
    "timestamp" : "03:42.560-03:44.560",
    "text" : "64"
  },
  {
    "text" : "65",
    "timestamp" : "03:44.560-03:48.560"
  },
  {
    "text" : "65",
    "timestamp" : "03:48.560-03:54.660"
  },
  {
    "text" : "65",
    "timestamp" : "03:54.660-03:54.660"
  },
  {
    "timestamp" : "03:54.660-03:56.660",
    "text" : "67"
  },
  {
    "timestamp" : "03:56.660-03:58.100",
    "text" : "67"
  },
  {
    "text" : "68",
    "timestamp" : "03:58.100-03:58.680"
  },
  {
    "timestamp" : "03:58.680-03:58.960",
    "text" : "65"
  },
  {
    "text" : "67",
    "timestamp" : "03:58.960-04:00.100"
  },
  {
    "timestamp" : "04:00.100-04:01.100",
    "text" : "68"
  },
  {
    "timestamp" : "04:01.100-04:01.680",
    "text" : "68"
  },
  {
    "text" : "69",
    "timestamp" : "04:01.680-04:03.100"
  },
  {
    "timestamp" : "04:03.100-04:04.100",
    "text" : "60"
  },
  {
    "timestamp" : "04:04.100-04:05.100",
    "text" : "60"
  },
  {
    "timestamp" : "04:05.100-04:05.100",
    "text" : "60"
  },
  {
    "timestamp" : "04:05.100-04:09.020",
    "text" : "60"
  },
  {
    "text" : "70",
    "timestamp" : "04:09.020-04:09.640"
  },
  {
    "text" : "71, 72, 73, 74, 75, 76, 77, 78,",
    "timestamp" : "04:09.640-04:39.600"
  },
  {
    "timestamp" : "04:39.600-05:07.360",
    "text" : "78, 79, 80, 81, 82, 83, 84, 85,"
  },
  {
    "timestamp" : "05:07.360-05:27.100",
    "text" : "86, 87, 88, 89, 90,"
  },
  {
    "text" : "91, 92, 93, 94, 95, 96, 97,",
    "timestamp" : "05:27.100-05:56.100"
  },
  {
    "text" : "98, 99, 100, 101, 102, 103, 104,",
    "timestamp" : "05:56.100-06:22.760"
  },
  {
    "text" : "105, 106, 107, 108, 109, 110, 111,",
    "timestamp" : "06:23.100-06:50.920"
  },
  {
    "timestamp" : "06:50.920-06:54.640",
    "text" : "112"
  },
  {
    "text" : "113",
    "timestamp" : "06:54.640-06:58.800"
  },
  {
    "text" : "114",
    "timestamp" : "06:58.800-07:02.680"
  },
  {
    "timestamp" : "07:02.680-07:06.520",
    "text" : "115"
  },
  {
    "text" : "116",
    "timestamp" : "07:06.520-07:10.300"
  },
  {
    "timestamp" : "07:10.300-07:15.160",
    "text" : "117"
  },
  {
    "timestamp" : "07:15.160-07:18.960",
    "text" : "118"
  },
  {
    "text" : "119",
    "timestamp" : "07:18.960-07:23.160"
  },
  {
    "text" : "120",
    "timestamp" : "07:23.160-07:27.180"
  },
  {
    "text" : "121",
    "timestamp" : "07:27.180-07:31.480"
  },
  {
    "timestamp" : "07:31.480-07:36.360",
    "text" : "122"
  },
  {
    "text" : "130",
    "timestamp" : "07:36.360-07:40.960"
  },
  {
    "text" : "140",
    "timestamp" : "07:40.960-07:45.060"
  },
  {
    "text" : "200",
    "timestamp" : "07:45.060-07:48.940"
  },
  {
    "timestamp" : "07:48.940-07:53.140",
    "text" : "201"
  },
  {
    "text" : "202",
    "timestamp" : "07:53.140-07:56.040"
  },
  {
    "text" : "250",
    "timestamp" : "07:56.040-08:00.160"
  },
  {
    "text" : "1000",
    "timestamp" : "08:00.160-08:03.140"
  },
  {
    "text" : "1001",
    "timestamp" : "08:03.140-08:07.140"
  },
  {
    "text" : "2000",
    "timestamp" : "08:07.140-08:09.140"
  },
  {
    "text" : "20000",
    "timestamp" : "08:09.140-08:13.340"
  },
  {
    "timestamp" : "08:13.340-08:15.240",
    "text" : "500000"
  },
  {
    "text" : "500000",
    "timestamp" : "08:15.240-08:19.860"
  },
  {
    "text" : "1 million",
    "timestamp" : "08:19.860-08:24.000"
  },
  {
    "timestamp" : "08:24.000-08:26.920",
    "text" : "We'll see you guys next time."
  },
  {
    "timestamp" : "08:26.920-08:56.900",
    "text" : "Thank you."
  }
]